pgpy_dtc/__init__.py
pgpy_dtc/_curves.py
pgpy_dtc/constants.py
pgpy_dtc/decorators.py
pgpy_dtc/errors.py
pgpy_dtc/pgp.py
pgpy_dtc/symenc.py
pgpy_dtc/types.py
pgpy_dtc/packet/__init__.py
pgpy_dtc/packet/fields.py
pgpy_dtc/packet/packets.py
pgpy_dtc/packet/types.py
pgpy_dtc/packet/subpackets/__init__.py
pgpy_dtc/packet/subpackets/signature.py
pgpy_dtc/packet/subpackets/types.py
pgpy_dtc/packet/subpackets/userattribute.py
PGPy_dtc-0.1.1.dist-info/LICENSE
PGPy_dtc-0.1.1.dist-info/METADATA
PGPy_dtc-0.1.1.dist-info/WHEEL
PGPy_dtc-0.1.1.dist-info/top_level.txt
PGPy_dtc-0.1.1.dist-info/zip-safe
PGPy_dtc-0.1.1.dist-info/RECORD
